libhodgkin_huxley.so
sanafecpp.cpython-39-x86_64-linux-gnu.so
sanafe/__init__.py
sanafe/fugu.py
sanafe/lava.py
sanafe/layers.py
sanafe/tutorial.py
sanafe.libs/libgomp-870cb1d0.so.1.0.0
sanafe-2.1.1.dist-info/METADATA
sanafe-2.1.1.dist-info/WHEEL
sanafe-2.1.1.dist-info/top_level.txt
sanafe-2.1.1.dist-info/RECORD
sanafe-2.1.1.dist-info/licenses/LICENSE
