Metadata-Version: 2.4
Name: sanafe
Version: 2.1.1
Summary: SANA-FE: Simulating Advanced Neuromorphic Architectures for Fast Exploration
Home-page: https://github.com/SLAM-Lab/SANA-FE
Author: James Boyle
Author-email: james.boyle@utexas.edu
Requires-Python: >=3.8
License-File: LICENSE
Dynamic: author
Dynamic: author-email
Dynamic: description
Dynamic: description-content-type
Dynamic: home-page
Dynamic: license-file
Dynamic: requires-python
Dynamic: summary
